aws_solutions_constructs/aws_lambda_step_function/__init__.py
aws_solutions_constructs/aws_lambda_step_function/py.typed
aws_solutions_constructs/aws_lambda_step_function/_jsii/__init__.py
aws_solutions_constructs/aws_lambda_step_function/_jsii/aws-lambda-step-function@1.181.1.jsii.tgz
aws_solutions_constructs.aws_lambda_step_function-1.181.1.dist-info/LICENSE
aws_solutions_constructs.aws_lambda_step_function-1.181.1.dist-info/METADATA
aws_solutions_constructs.aws_lambda_step_function-1.181.1.dist-info/WHEEL
aws_solutions_constructs.aws_lambda_step_function-1.181.1.dist-info/top_level.txt
aws_solutions_constructs.aws_lambda_step_function-1.181.1.dist-info/RECORD
