Metadata-Version: 2.1
Name: aws-solutions-constructs.aws-lambda-step-function
Version: 1.181.1
Summary: CDK constructs for defining an interaction between an AWS Lambda function and an AWS Step Function.
Home-page: https://github.com/awslabs/aws-solutions-constructs.git
Author: Amazon Web Services
License: Apache-2.0
Project-URL: Source, https://github.com/awslabs/aws-solutions-constructs.git
Platform: UNKNOWN
Classifier: Intended Audience :: Developers
Classifier: Operating System :: OS Independent
Classifier: Programming Language :: JavaScript
Classifier: Programming Language :: Python :: 3 :: Only
Classifier: Programming Language :: Python :: 3.7
Classifier: Programming Language :: Python :: 3.8
Classifier: Programming Language :: Python :: 3.9
Classifier: Programming Language :: Python :: 3.10
Classifier: Typing :: Typed
Classifier: License :: OSI Approved
Requires-Python: ~=3.7
License-File: LICENSE
Requires-Dist: aws-cdk.aws-cloudwatch (==1.181.1)
Requires-Dist: aws-cdk.aws-ec2 (==1.181.1)
Requires-Dist: aws-cdk.aws-lambda (==1.181.1)
Requires-Dist: aws-cdk.aws-logs (==1.181.1)
Requires-Dist: aws-cdk.aws-stepfunctions (==1.181.1)
Requires-Dist: aws-cdk.core (==1.181.1)
Requires-Dist: aws-solutions-constructs.aws-lambda-stepfunctions (==1.181.1)
Requires-Dist: aws-solutions-constructs.core (==1.181.1)
Requires-Dist: constructs (<4.0.0,>=3.2.0)
Requires-Dist: jsii (<2.0.0,>=1.71.0)
Requires-Dist: publication (>=0.0.3)
Requires-Dist: typeguard (~=2.13.3)
